README.rst
bootstrap.py
buildout.cfg
setup.cfg
setup.py
docs/Makefile
docs/make.bat
docs/source/HISTORY.rst
docs/source/README.rst
docs/source/conf.py
docs/source/index.rst
zopyx/__init__.py
zopyx.existdb.egg-info/PKG-INFO
zopyx.existdb.egg-info/SOURCES.txt
zopyx.existdb.egg-info/dependency_links.txt
zopyx.existdb.egg-info/entry_points.txt
zopyx.existdb.egg-info/namespace_packages.txt
zopyx.existdb.egg-info/not-zip-safe
zopyx.existdb.egg-info/requires.txt
zopyx.existdb.egg-info/top_level.txt
zopyx/existdb/__init__.py
zopyx/existdb/configure.zcml
zopyx/existdb/connector.py
zopyx/existdb/header.txt
zopyx/existdb/i18n.py
zopyx/existdb/interfaces.py
zopyx/existdb/logger.py
zopyx/existdb/meta.zcml
zopyx/existdb/browser/__init__.py
zopyx/existdb/browser/ace_editor.pt
zopyx/existdb/browser/api.py
zopyx/existdb/browser/config.py
zopyx/existdb/browser/configure.zcml
zopyx/existdb/browser/connector.py
zopyx/existdb/browser/connector_log.pt
zopyx/existdb/browser/connector_view.pt
zopyx/existdb/browser/connector_views.py
zopyx/existdb/browser/connector_zip_import.pt
zopyx/existdb/browser/controlpanel.py
zopyx/existdb/browser/error.pt
zopyx/existdb/browser/html_view.pt
zopyx/existdb/browser/view_registry.py
zopyx/existdb/browser/resources/local.js
zopyx/existdb/browser/resources/styles.css
zopyx/existdb/browser/resources/ace-builds/ChangeLog.txt
zopyx/existdb/browser/resources/ace-builds/LICENSE
zopyx/existdb/browser/resources/ace-builds/README.md
zopyx/existdb/browser/resources/ace-builds/editor.html
zopyx/existdb/browser/resources/ace-builds/kitchen-sink.html
zopyx/existdb/browser/resources/ace-builds/demo/autocompletion.html
zopyx/existdb/browser/resources/ace-builds/demo/autoresize.html
zopyx/existdb/browser/resources/ace-builds/demo/chromevox.html
zopyx/existdb/browser/resources/ace-builds/demo/emmet.html
zopyx/existdb/browser/resources/ace-builds/demo/ie7.html
zopyx/existdb/browser/resources/ace-builds/demo/iframe.html
zopyx/existdb/browser/resources/ace-builds/demo/keyboard_shortcuts.html
zopyx/existdb/browser/resources/ace-builds/demo/modelist.html
zopyx/existdb/browser/resources/ace-builds/demo/r.js
zopyx/existdb/browser/resources/ace-builds/demo/scrollable-page.html
zopyx/existdb/browser/resources/ace-builds/demo/settings_menu.html
