Metadata-Version: 1.0
Name: zopyx.existdb
Version: 0.2.11.1
Summary: Plone-ExistDB integration
Home-page: http://pypi.python.org/pypi/zopyx.existdb
Author: Andreas Jung
Author-email: info@zopyx.com
License: GPL
Keywords: exist-db basex existdb Plone XML Python WebDAV
Platform: UNKNOWN
Classifier: Programming Language :: Python
Classifier: Framework :: Plone
Classifier: Framework :: Plone :: 4.3
Classifier: Framework :: Plone :: 5.0
Classifier: Framework :: Zope2
Classifier: Topic :: Software Development :: Libraries :: Python Modules
